{
  "vendors~attachment-field~multi-attachment-field~multi-group-field~multi-post-field~post-field.js": "vendors~attachment-field~multi-attachment-field~multi-group-field~multi-post-field~post-field.d2c71a53bc4a6879.js",
  "vendors~multi-post-field~multi-select-field~post-field~select-field.js": "vendors~multi-post-field~multi-select-field~post-field~select-field.d2c71a53bc4a6879.js",
  "attachment-field.js": "attachment-field.d2c71a53bc4a6879.js",
  "button-field.js": "button-field.d2c71a53bc4a6879.js",
  "checkbox-field.js": "checkbox-field.d2c71a53bc4a6879.js",
  "code-field.js": "code-field.d2c71a53bc4a6879.js",
  "color-field.js": "color-field.d2c71a53bc4a6879.js",
  "date-field.js": "date-field.d2c71a53bc4a6879.js",
  "datetime-field.js": "datetime-field.d2c71a53bc4a6879.js",
  "email-field.js": "email-field.d2c71a53bc4a6879.js",
  "group-field.js": "group-field.d2c71a53bc4a6879.js",
  "hidden-field.js": "hidden-field.d2c71a53bc4a6879.js",
  "html-field.js": "html-field.d2c71a53bc4a6879.js",
  "month-field.js": "month-field.d2c71a53bc4a6879.js",
  "multi-attachment-field.js": "multi-attachment-field.d2c71a53bc4a6879.js",
  "multi-group-field.js": "multi-group-field.d2c71a53bc4a6879.js",
  "multi-post-field.js": "multi-post-field.d2c71a53bc4a6879.js",
  "multi-select-field.js": "multi-select-field.d2c71a53bc4a6879.js",
  "multi-toggle-field.js": "multi-toggle-field.d2c71a53bc4a6879.js",
  "number-field.js": "number-field.d2c71a53bc4a6879.js",
  "password-field.js": "password-field.d2c71a53bc4a6879.js",
  "post-field.js": "post-field.d2c71a53bc4a6879.js",
  "react-field.js": "react-field.d2c71a53bc4a6879.js",
  "select-field.js": "select-field.d2c71a53bc4a6879.js",
  "separator-field.js": "separator-field.d2c71a53bc4a6879.js",
  "tel-field.js": "tel-field.d2c71a53bc4a6879.js",
  "text-field.js": "text-field.d2c71a53bc4a6879.js",
  "textarea-field.js": "textarea-field.d2c71a53bc4a6879.js",
  "time-field.js": "time-field.d2c71a53bc4a6879.js",
  "title-field.js": "title-field.d2c71a53bc4a6879.js",
  "toggle-field.js": "toggle-field.d2c71a53bc4a6879.js",
  "url-field.js": "url-field.d2c71a53bc4a6879.js",
  "vendors~color-field.js": "vendors~color-field.d2c71a53bc4a6879.js",
  "vendors~tel-field.js": "vendors~tel-field.d2c71a53bc4a6879.js",
  "vendors~wysiwyg-field.js": "vendors~wysiwyg-field.d2c71a53bc4a6879.js",
  "week-field.js": "week-field.d2c71a53bc4a6879.js",
  "wpify-custom-blocks.css": "wpify-custom-blocks.css",
  "wpify-custom-blocks.js": "wpify-custom-blocks.js",
  "wpify-custom-fields.css": "wpify-custom-fields.css",
  "wpify-custom-fields.js": "wpify-custom-fields.js",
  "wysiwyg-field.js": "wysiwyg-field.d2c71a53bc4a6879.js",
  "assets.php": "assets.php",
  "images/flags.png": "images/flags.007b2705.png",
  "images/flags@2x.png": "images/flags@2x.9d5328fb.png"
}